README.rst
setup.cfg
setup.py
kawaii/__init__.py
kawaii/config.py
kawaii/types.py
kawaii.egg-info/PKG-INFO
kawaii.egg-info/SOURCES.txt
kawaii.egg-info/dependency_links.txt
kawaii.egg-info/top_level.txt
kawaii/arboretum/__init__.py
kawaii/arboretum/combine.py
kawaii/arboretum/parse.py
tests/arboterum_tests/__init__.py
tests/arboterum_tests/test_parse.py
tests/fixtures/__init__.py
tests/fixtures/arboterum.py
tests/strategies/__init__.py
tests/strategies/sourceables/__init__.py
tests/strategies/sourceables/classes.py
tests/strategies/sourceables/functions.py
tests/strategies/sourceables/modules.py
tests/strategies/sourceables/utils.py