Metadata-Version: 1.1
Name: kawaii
Version: 0.0.0
Summary: UNKNOWN
Home-page: https://github.com/lycantropos/kawaii/
Author: Azat Ibrakov
Author-email: azatibrakov@gmail.com
License: UNKNOWN
Download-URL: https://github.com/lycantropos/kawaii/archive/master.zip
Platform: UNKNOWN
